awspricemanager/__init__.py
awspricemanager/constants.py
awspricemanager/pricemanager.py
awspricemanager-0.0.14.dist-info/DESCRIPTION.rst
awspricemanager-0.0.14.dist-info/METADATA
awspricemanager-0.0.14.dist-info/RECORD
awspricemanager-0.0.14.dist-info/WHEEL
awspricemanager-0.0.14.dist-info/metadata.json
awspricemanager-0.0.14.dist-info/top_level.txt
offers/__init__.py
offers/ec2.py
offers/offer.py
